cartoasync/__init__.py
cartoasync/auth.py
cartoasync/exceptions.py
cartoasync/sql_client.py
geolibs_cartoasync-0.0.4.dist-info/LICENSE
geolibs_cartoasync-0.0.4.dist-info/WHEEL
geolibs_cartoasync-0.0.4.dist-info/METADATA
geolibs_cartoasync-0.0.4.dist-info/RECORD
