Metadata-Version: 2.1
Name: geolibs-cartoasync
Version: 0.0.4
Summary: GeoLibs CARTOasync
Home-page: https://github.com/GeographicaGS/GeoLibs-CARTOasync
License: MIT
Author: Geographica
Author-email: hello@geographica.com
Requires-Python: >=3.7,<4.0
Classifier: License :: OSI Approved :: MIT License
Classifier: Programming Language :: Python :: 3
Classifier: Programming Language :: Python :: 3.7
Requires-Dist: aiohttp (>=3.5,<4.0)
